counter_project/counter.sv
module counter(
    input logic clk,
    input logic rst,
    input logic en,
    output logic [7:0] count 
);

always_ff @(posedge clk or posedge rst) begin
    if (rst)
        count <= 8'd0;
    else if (en)
        count <= count + 8'd1;
end

endmodule

counter_project/tb_counter.sv
module tb_counter;
    logic clk;
    logic rst;
    logic en;
    logic [7:0] count;

    counter uut(
        .clk(clk),
        .rst(rst),
        .en(en),
        .count(count)
    );

    always #5 clk = ~clk;
    
    initial begin
        $dumpfile ("counter.vcd");
        $dumpvars (0, tb_counter);
        clk = 0;
        rst = 1;
        en = 0;
        #10 rst = 0;
        #10 en = 1;
        #30 en = 0;
        #20 en = 1;
        #50 rst = 1;
        #20 rst = 0;
        #20 en = 0;
        #20 $finish;
    end

endmodule

counter_project/counter.vcd
$date
	Mon Feb 23 16:39:28 2026
$end
$version
	Icarus Verilog
$end
$timescale
	1s
$end
$scope module tb_counter $end
$var wire 8 ! count [7:0] $end
$var reg 1 " clk $end
$var reg 1 # en $end
$var reg 1 $ rst $end
$scope module uut $end
$var wire 1 " clk $end
$var wire 1 # en $end
$var wire 1 $ rst $end
$var reg 8 % count [7:0] $end
$upscope $end
$upscope $end
$enddefinitions $end
$comment Show the parameter values. $end
$dumpall
$end
#0
$dumpvars
b0 %
1$
0#
0"
b0 !
$end
#5
1"
#10
0"
0$
#15
1"
#20
0"
1#
#25
b1 !
b1 %
1"
#30
0"
#35
b10 !
b10 %
1"
#40
0"
#45
b11 !
b11 %
1"
#50
0"
0#
#55
1"
#60
0"
#65
1"
#70
0"
1#
#75
b100 !
b100 %
1"
#80
0"
#85
b101 !
b101 %
1"
#90
0"
#95
b110 !
b110 %
1"
#100
0"
#105
b111 !
b111 %
1"
#110
0"
#115
b1000 !
b1000 %
1"
#120
b0 !
b0 %
0"
1$
#125
1"
#130
0"
#135
1"
#140
0"
0$
#145
b1 !
b1 %
1"
#150
0"
#155
b10 !
b10 %
1"
#160
0"
0#
