register_project/register.sv
module register(
    input logic clk,
    input logic rst,
    input logic en,
    input logic [7:0] d,
    output logic [7:0] q
);

always_ff @(posedge clk or posedge rst) begin
    if (rst)
        q<= 8'b00000000;
    else if (en)
        q <= d;
end

endmodule

register_project/tb_register.sv
`timescale 1ns/1ps
module tb_register;

logic clk;
logic rst;
logic en;
logic [7:0] d;
logic [7:0] q;

register uut (
    .clk(clk),
    .rst(rst),
    .en(en),
    .d(d),
    .q(q)
);

always #5 clk = ~clk;

initial begin
    $dumpfile("register.vcd");
    $dumpvars(0, tb_register);

    clk = 0;
    rst = 1;
    en = 0;
    d = 8'd0;

    #10 rst = 0;

    #10 en = 1; d = 8'd5;
    #10 d = 8'd10;  
    #10 en = 0; d = 8'd20;
    #10 en = 1; d = 8'd42;

    #20 $finish;
end

initial begin

    forever begin
        @(posedge clk);
        #1;
        
        if (rst) begin
            if (q == 8'd0) 
                $display("PASS: register reset to 0");
            else
                $display("ERROR: q is not 0 during reset");
        end

        else if (en) begin
            if (q == d)
                $display("PASS @%0t: register captured input %0d", $time, q);
            else
                $display("ERROR @%0t: expected %0d got %0d", $time, d, q);
        end
    end
end


endmodule

register_project/register.vcd
$date
	Mon Feb 23 16:41:00 2026
$end
$version
	Icarus Verilog
$end
$timescale
	1ps
$end
$scope module tb_register $end
$var wire 8 ! q [7:0] $end
$var reg 1 " clk $end
$var reg 8 # d [7:0] $end
$var reg 1 $ en $end
$var reg 1 % rst $end
$scope module uut $end
$var wire 1 " clk $end
$var wire 8 & d [7:0] $end
$var wire 1 $ en $end
$var wire 1 % rst $end
$var reg 8 ' q [7:0] $end
$upscope $end
$upscope $end
$enddefinitions $end
$comment Show the parameter values. $end
$dumpall
$end
#0
$dumpvars
b0 '
b0 &
1%
0$
b0 #
0"
b0 !
$end
#5000
1"
#10000
0"
0%
#15000
1"
#20000
0"
b101 #
b101 &
1$
#25000
b101 !
b101 '
1"
#30000
0"
b1010 #
b1010 &
#35000
b1010 !
b1010 '
1"
#40000
0"
b10100 #
b10100 &
0$
#45000
1"
#50000
0"
b101010 #
b101010 &
1$
#55000
b101010 !
b101010 '
1"
