register_project/register_mygo.sv
module register_mygo(
    input logic clk,
    input logic rst,
    input logic [7:0] d,
    output logic [7:0] q
);

always_ff @(posedge clk or posedge rst) begin
    if (rst)
        q <= 0;
    else
        q <= d;
end

endmodule

register_project/tb_register_mygo.sv
`timescale 1ns/1ps
module tb_register_mygo;

logic clk;
logic rst;
logic [7:0] d;
logic [7:0] q;

register_mygo uut(
    .clk(clk),
    .rst(rst),
    .d(d),
    .q(q)
);

always #5 clk = ~clk;

initial begin
    $dumpfile("register_mygo.vcd");
    $dumpvars(0, tb_register_mygo);

    clk = 0;
    rst = 1;
    d = 0;
    
    #10 rst = 0;
    #10 d = 20;
    #10 d = 10;
    #10 d = 34;
    #10 d = 6;
    #3 d = 104;
    #3 d = 67;
    #4 d = 5;
    #10 rst = 1;
    #10 rst = 0;
    #20 $finish;
end
endmodule

register_project/register_mygo.vcd
$date
	Mon Feb 23 16:43:42 2026
$end
$version
	Icarus Verilog
$end
$timescale
	1ps
$end
$scope module tb_register_mygo $end
$var wire 8 ! q [7:0] $end
$var reg 1 " clk $end
$var reg 8 # d [7:0] $end
$var reg 1 $ rst $end
$scope module uut $end
$var wire 1 " clk $end
$var wire 8 % d [7:0] $end
$var wire 1 $ rst $end
$var reg 8 & q [7:0] $end
$upscope $end
$upscope $end
$enddefinitions $end
$comment Show the parameter values. $end
$dumpall
$end
#0
$dumpvars
b0 &
b0 %
1$
b0 #
0"
b0 !
$end
#5000
1"
#10000
0"
0$
#15000
1"
#20000
0"
b10100 #
b10100 %
#25000
b10100 !
b10100 &
1"
#30000
0"
b1010 #
b1010 %
#35000
b1010 !
b1010 &
1"
#40000
0"
b100010 #
b100010 %
#45000
b100010 !
b100010 &
1"
#50000
0"
b110 #
b110 %
#53000
b1101000 #
b1101000 %
#55000
b1101000 !
b1101000 &
1"
#56000
b1000011 #
b1000011 %
#60000
b101 #
b101 %
0"
#65000
b101 !
b101 &
1"
#70000
b0 !
b0 &
0"
1$
#75000
1"
#80000
0"
0$
#85000
b101 !
b101 &
1"
