mux_project/mux_proj.sv
module mux_proj(
    input logic in0,
    input logic in1,
    input logic sel,
    output logic y
);

assign y  = sel ? in1 : in0;

endmodule

mux_project/tb_mux_proj.sv
module tb_mux_proj;

logic in0;
logic in1;
logic sel;
logic y;

mux_proj uut(
    .in0(in0),
    .in1(in1),
    .sel(sel),
    .y(y)
);

task run_case(input logic t_in0, input logic t_in1, input logic t_sel);
    logic expected;

    in0 = t_in0;
    in1 = t_in1;
    sel = t_sel;

    #1;

    expected = t_sel ? t_in1 : t_in0;

    if (y !== expected) begin
        $display("ERROR at time=%0t in0=%0d in1=%0d sel=%0d | expected=%0d got=%0d", $time, t_in0, t_in1, t_sel, expected, y);
        $finish;
    end
endtask


initial begin
    $dumpfile("mux_proj.vcd");
    $dumpvars(0, tb_mux_proj);
    run_case(0,1,0);
    run_case(0,1,1);
    run_case(1,0,0);
    run_case(1,0,1);
    run_case(0,0,0);
    run_case(0,0,1);
    run_case(1,1,0);
    run_case(1,1,1);

    $display("All tests passed!");
    $finish;
end

endmodule

mux_project/mux_proj.vcd
$date
	Mon Feb 23 16:09:46 2026
$end
$version
	Icarus Verilog
$end
$timescale
	1s
$end
$scope module tb_mux_proj $end
$var wire 1 ! y $end
$var reg 1 " in0 $end
$var reg 1 # in1 $end
$var reg 1 $ sel $end
$scope module uut $end
$var wire 1 " in0 $end
$var wire 1 # in1 $end
$var wire 1 $ sel $end
$var wire 1 ! y $end
$upscope $end
$scope task run_case $end
$var reg 1 % expected $end
$var reg 1 & t_in0 $end
$var reg 1 ' t_in1 $end
$var reg 1 ( t_sel $end
$upscope $end
$upscope $end
$enddefinitions $end
$comment Show the parameter values. $end
$dumpall
$end
#0
$dumpvars
0(
1'
0&
x%
0$
1#
0"
0!
$end
#1
1!
1$
1(
0%
#2
0$
0#
1"
0(
0'
1&
1%
#3
0!
1$
1(
#4
0$
0"
0(
0&
0%
#5
1$
1(
#6
1!
0$
1#
1"
0(
1'
1&
#7
1$
1(
1%
